Metadata-Version: 2.1
Name: pyarray
Version: 0.2
Summary: A small array utlity library
Home-page: https://github.com/pranavbaburaj/array-utility
Author: Pranav Baburaj
License: UNKNOWN
Platform: UNKNOWN
Classifier: Programming Language :: Python :: 3
Classifier: License :: OSI Approved :: MIT License
Classifier: Operating System :: OS Independent
Requires-Python: >=3.6
